{
  "state_hash": "4ecee967bbdbbddc4307fd9496ed159e914014d5f129c3267c967a3bd816ba93",
  "tested_actions": [
    {
      "action": "RESET",
      "changed_cells": 2,
      "effect_type": "small_change",
      "next_state_hash": "d4665b979aa743fe2efe0b843bb82cfdd9f43545d38a7202ebc33528a9420fa8",
      "terminal": false
    },
    {
      "action": "ACTION1",
      "changed_cells": null,
      "effect_type": "untested",
      "next_state_hash": null,
      "terminal": null
    },
    {
      "action": "ACTION2",
      "changed_cells": null,
      "effect_type": "untested",
      "next_state_hash": null,
      "terminal": null
    },
    {
      "action": "ACTION3",
      "changed_cells": null,
      "effect_type": "untested",
      "next_state_hash": null,
      "terminal": null
    },
    {
      "action": "ACTION4",
      "changed_cells": null,
      "effect_type": "untested",
      "next_state_hash": null,
      "terminal": null
    },
    {
      "action": "ACTION5",
      "changed_cells": null,
      "effect_type": "untested",
      "next_state_hash": null,
      "terminal": null
    },
    {
      "action": "ACTION6",
      "changed_cells": null,
      "effect_type": "untested",
      "next_state_hash": null,
      "terminal": null
    },
    {
      "action": "ACTION7",
      "changed_cells": null,
      "effect_type": "untested",
      "next_state_hash": null,
      "terminal": null
    }
  ]
}